sanic_redis_extend/__init__.py
sanic_redis_extend/core.py
sanic_redis_extend-0.0.1.dist-info/METADATA
sanic_redis_extend-0.0.1.dist-info/WHEEL
sanic_redis_extend-0.0.1.dist-info/top_level.txt
sanic_redis_extend-0.0.1.dist-info/RECORD
