Metadata-Version: 2.1
Name: sanic-redis-extend
Version: 0.0.1
Summary: sanic redis extend
Home-page: https://github.com/lvyunze/sanic_redis_extend
Author: lvyunze
Author-email: 17817462542@163.com
Keywords: sanic redis extend
Classifier: Programming Language :: Python :: 3
Classifier: License :: OSI Approved :: MIT License
Classifier: Operating System :: OS Independent
Requires-Python: >=3.6
Requires-Dist: aioredis (==2.0.1)
Requires-Dist: sanic (==22.6.0)
